rpygrep/__init__.py
rpygrep/base.py
rpygrep/helpers.py
rpygrep/py.typed
rpygrep/types.py
rpygrep-0.2.1.dist-info/WHEEL
rpygrep-0.2.1.dist-info/METADATA
rpygrep-0.2.1.dist-info/RECORD
