Metadata-Version: 2.3
Name: rpygrep
Version: 0.2.1
Summary: A Python wrapper for ripgrep
Author: Strawgate
Author-email: Strawgate <williamseaston@gmail.com>
Classifier: License :: OSI Approved :: MIT License
Requires-Dist: pydantic>=2.10.6
Requires-Dist: ripgrep>=14.1.0
Requires-Python: >=3.10
